topscore/__init__.py
topscore/client.py
topscore-0.0.2.dist-info/LICENSE
topscore-0.0.2.dist-info/METADATA
topscore-0.0.2.dist-info/WHEEL
topscore-0.0.2.dist-info/top_level.txt
topscore-0.0.2.dist-info/RECORD
