Metadata-Version: 2.1
Name: topscore
Version: 0.0.2
Summary: Topscore API python client
Home-page: https://github.com/cherianb59/topscore
Author: Ben Cherian
Author-email: 
Project-URL: Homepage, https://github.com/cherianb59/topscore
Project-URL: Issues, https://github.com/cherianb59/topscore/issues
Classifier: Programming Language :: Python :: 3
Classifier: Operating System :: OS Independent
Requires-Python: >=3.8
License-File: LICENSE
Requires-Dist: requests
Requires-Dist: aiohttp
Requires-Dist: beautifulsoup4
